<?xml version="1.0" encoding="UTF-8"?>
<MetaPed>
 <outfits itemType="MetaPedOutfit">
  <Item>
   <name>meta_outfit_cold_weather</name>
   <ethnicity>caucasian</ethnicity>
   <slodDwd>MKzClGA_0x5DB807E3</slodDwd>
   <voiceGroup />
   <damagePack />
   <goreType />
   <scale value="0" />
   <cutsceneScale value="0" />
   <scaleRandomOffset value="0" />
   <coatShine value="0" />
   <coatShineBase value="0" />
   <coatShineMin value="0" />
   <coatShineMax value="1" />
   <eyeRedness value="0" />
   <removeLimbBone>ID_INVALID</removeLimbBone>
   <fullOutfit value="True" />
   <priorityLoad value="False" />
   <preStream value="False" />
   <assets />
   <explicitAssets itemType="MetaPedDefExplicitAsset">
    <Item>
     <drawable>dUMCATA_0x44D000AB</drawable>
     <albedo>ZxomvaA_0xFB230229</albedo>
     <normal>KbSIdEA_0xF88378CA</normal>
     <material>adwJvJA_0x8C0FCCF0</material>
     <palette />
     <tint0 value="0" />
     <tint1 value="0" />
     <tint2 value="0" />
     <probability value="255" />
    </Item>
    <Item>
     <drawable>HHKUMEA_0x7D8435A8</drawable>
     <albedo>mRuWHEA_0x2CEC7FFB</albedo>
     <normal>vVTUFEA_0x3752B4EC</normal>
     <material>GnIFkEA_0x56DB20E8</material>
     <palette />
     <tint0 value="0" />
     <tint1 value="0" />
     <tint2 value="0" />
     <probability value="255" />
    </Item>
    <Item>
     <drawable>dOhuYLA_0xF54F9CC0</drawable>
     <albedo>dNvSlLA_0xDDE7B87C</albedo>
     <normal>YGCezGA_0x8966E537</normal>
     <material>xyDnBDA_0xFB5B13DF</material>
     <palette />
     <tint0 value="0" />
     <tint1 value="0" />
     <tint2 value="0" />
     <probability value="255" />
    </Item>
    <Item>
     <drawable>KlCXtIA_0x30907A5A</drawable>
     <albedo>eye_cap_gen_0000_c0_000_ab</albedo>
     <normal>eye_cap_gen_0000_c0_000_nm</normal>
     <material>eye_cap_gen_0000_c0_000_m</material>
     <palette />
     <tint0 value="0" />
     <tint1 value="0" />
     <tint2 value="0" />
     <probability value="255" />
    </Item>
    <Item>
     <drawable>smMlOEA_0x251F0702</drawable>
     <albedo>hkYtMLA_0xC7F189E5</albedo>
     <normal>YGeZHQA_0x4147A218</normal>
     <material>ZDcsoDA_0xCF772381</material>
     <palette />
     <tint0 value="0" />
     <tint1 value="0" />
     <tint2 value="0" />
     <probability value="255" />
    </Item>
    <Item>
     <drawable>mJZjigA_0x03E1C1F7</drawable>
     <albedo>ZXPYkCA_0x41A45058</albedo>
     <normal>eyes_gen_0000_c0_000_nm</normal>
     <material>eyes_gen_0000_c0_000_m</material>
     <palette />
     <tint0 value="0" />
     <tint1 value="0" />
     <tint2 value="0" />
     <probability value="255" />
    </Item>
    <Item>
     <drawable>YKiDhAA_0x35F23327</drawable>
     <albedo>MVgiGFA_0x356F2BE5</albedo>
     <normal>taBnCBA_0xF041A3A7</normal>
     <material>RxoqujA_0x9282F752</material>
     <palette />
     <tint0 value="0" />
     <tint1 value="0" />
     <tint2 value="0" />
     <probability value="255" />
    </Item>
    <Item>
     <drawable>DnMGtGA_0xFC54399B</drawable>
     <albedo>hair_gen_999_c0_999_ab</albedo>
     <normal>hair_gen_999_c0_999_nm</normal>
     <material>hair_gen_999_c0_999_m</material>
     <palette>gCrTlMA_0xDFB1F64C</palette>
     <tint0 value="8" />
     <tint1 value="250" />
     <tint2 value="135" />
     <probability value="255" />
    </Item>
    <Item>
     <drawable>KHTsMKA_0x24496A6D</drawable>
     <albedo>WkAfpPA_0xC03F9101</albedo>
     <normal>JTCFcPA_0x6C35A841</normal>
     <material>APyTsUA_0x1BE249F0</material>
     <palette />
     <tint0 value="0" />
     <tint1 value="0" />
     <tint2 value="0" />
     <probability value="255" />
    </Item>
    <Item>
     <drawable>qylauKA_0x2601A033</drawable>
     <albedo>XBZEyHA_0x2D77CC6A</albedo>
     <normal>hand_fr1_000_c0_000_nm</normal>
     <material>hand_fr1_000_c0_000_m</material>
     <palette />
     <tint0 value="0" />
     <tint1 value="0" />
     <tint2 value="0" />
     <probability value="255" />
    </Item>
    <Item>
     <drawable>JUIEUqA_0xBD2338E5</drawable>
     <albedo>jJfqZAA_0x896C8656</albedo>
     <normal>TnAsxOA_0xC9B01E98</normal>
     <material>abVOsMA_0xC902FA5C</material>
     <palette />
     <tint0 value="0" />
     <tint1 value="0" />
     <tint2 value="0" />
     <probability value="255" />
    </Item>
    <Item>
     <drawable>rjJWIXA_0x1389AB66</drawable>
     <albedo>dsXYVMA_0xB23FA248</albedo>
     <normal>qQfjyKA_0xAA7A067D</normal>
     <material>ZNhsZdA_0x5F96AC1E</material>
     <palette />
     <tint0 value="0" />
     <tint1 value="0" />
     <tint2 value="0" />
     <probability value="255" />
    </Item>
    <Item>
     <drawable>QOlxHTA_0x799A41A2</drawable>
     <albedo>wXAGiUA_0x6415DE68</albedo>
     <normal>OhZVAYA_0xB9AF1EC5</normal>
     <material>rPhVwCA_0x1663F9CE</material>
     <palette />
     <tint0 value="0" />
     <tint1 value="0" />
     <tint2 value="0" />
     <probability value="255" />
    </Item>
    <Item>
     <drawable>RMFUvJA_0x4B8F1BF6</drawable>
     <albedo>YgpkJlA_0x7480EBA5</albedo>
     <normal>egoQWKA_0xEF1656DA</normal>
     <material>vhPnvMA_0xB3581CC7</material>
     <palette />
     <tint0 value="0" />
     <tint1 value="0" />
     <tint2 value="0" />
     <probability value="255" />
    </Item>
   </explicitAssets>
   <expressions itemType="MetaPedExpression">
    <Item>
     <id value="16009" />
     <value value="-0.1" />
    </Item>
    <Item>
     <id value="38169" />
     <value value="-0.87" />
    </Item>
    <Item>
     <id value="9586" />
     <value value="-0.4" />
    </Item>
   </expressions>
   <subOutfits />
   <variations />
   <tags>
    <Item>DuEerZA_0x92C43393</Item>
    <Item>hTzmBfA_0x4BFA4A07</Item>
    <Item>rRHQlJA_0x2F9EEF6E</Item>
   </tags>
   <shopItems />
  </Item>
  <Item>
   <name>meta_outfit_cool_weather</name>
   <ethnicity>caucasian</ethnicity>
   <slodDwd>MKzClGA_0x5DB807E3</slodDwd>
   <voiceGroup />
   <damagePack />
   <goreType />
   <scale value="0" />
   <cutsceneScale value="0" />
   <scaleRandomOffset value="0" />
   <coatShine value="0" />
   <coatShineBase value="0" />
   <coatShineMin value="0" />
   <coatShineMax value="1" />
   <eyeRedness value="0" />
   <removeLimbBone>ID_INVALID</removeLimbBone>
   <fullOutfit value="True" />
   <priorityLoad value="False" />
   <preStream value="False" />
   <assets />
   <explicitAssets itemType="MetaPedDefExplicitAsset">
    <Item>
     <drawable>HHKUMEA_0x7D8435A8</drawable>
     <albedo>mRuWHEA_0x2CEC7FFB</albedo>
     <normal>vVTUFEA_0x3752B4EC</normal>
     <material>GnIFkEA_0x56DB20E8</material>
     <palette />
     <tint0 value="0" />
     <tint1 value="0" />
     <tint2 value="0" />
     <probability value="255" />
    </Item>
    <Item>
     <drawable>cs_abigailroberts_fs1_coat_000</drawable>
     <albedo>FBZgKAA_0x3D219C8B</albedo>
     <normal>SYkFaeA_0x16CE2B0A</normal>
     <material>cdssMLA_0x3389B5DB</material>
     <palette />
     <tint0 value="0" />
     <tint1 value="0" />
     <tint2 value="0" />
     <probability value="255" />
    </Item>
    <Item>
     <drawable>KlCXtIA_0x30907A5A</drawable>
     <albedo>eye_cap_gen_0000_c0_000_ab</albedo>
     <normal>eye_cap_gen_0000_c0_000_nm</normal>
     <material>eye_cap_gen_0000_c0_000_m</material>
     <palette />
     <tint0 value="0" />
     <tint1 value="0" />
     <tint2 value="0" />
     <probability value="255" />
    </Item>
    <Item>
     <drawable>smMlOEA_0x251F0702</drawable>
     <albedo>hkYtMLA_0xC7F189E5</albedo>
     <normal>YGeZHQA_0x4147A218</normal>
     <material>ZDcsoDA_0xCF772381</material>
     <palette />
     <tint0 value="0" />
     <tint1 value="0" />
     <tint2 value="0" />
     <probability value="255" />
    </Item>
    <Item>
     <drawable>mJZjigA_0x03E1C1F7</drawable>
     <albedo>ZXPYkCA_0x41A45058</albedo>
     <normal>eyes_gen_0000_c0_000_nm</normal>
     <material>eyes_gen_0000_c0_000_m</material>
     <palette />
     <tint0 value="0" />
     <tint1 value="0" />
     <tint2 value="0" />
     <probability value="255" />
    </Item>
    <Item>
     <drawable>BbXwIgA_0xEE399D66</drawable>
     <albedo>hair_gen_999_c0_999_ab</albedo>
     <normal>hair_gen_999_c0_999_nm</normal>
     <material>hair_gen_999_c0_999_m</material>
     <palette>gCrTlMA_0xDFB1F64C</palette>
     <tint0 value="8" />
     <tint1 value="250" />
     <tint2 value="135" />
     <probability value="255" />
    </Item>
    <Item>
     <drawable>KHTsMKA_0x24496A6D</drawable>
     <albedo>WkAfpPA_0xC03F9101</albedo>
     <normal>JTCFcPA_0x6C35A841</normal>
     <material>APyTsUA_0x1BE249F0</material>
     <palette />
     <tint0 value="0" />
     <tint1 value="0" />
     <tint2 value="0" />
     <probability value="255" />
    </Item>
    <Item>
     <drawable>ylsILtA_0xF3253A77</drawable>
     <albedo>XBZEyHA_0x2D77CC6A</albedo>
     <normal>WSLhjNA_0x3C99B8E6</normal>
     <material>FkJmxKA_0x17BA170C</material>
     <palette />
     <tint0 value="0" />
     <tint1 value="0" />
     <tint2 value="0" />
     <probability value="255" />
    </Item>
    <Item>
     <drawable>ZTpXhhA_0x2146C6E0</drawable>
     <albedo>dsXYVMA_0xB23FA248</albedo>
     <normal>qQfjyKA_0xAA7A067D</normal>
     <material>ZNhsZdA_0x5F96AC1E</material>
     <palette />
     <tint0 value="0" />
     <tint1 value="0" />
     <tint2 value="0" />
     <probability value="255" />
    </Item>
    <Item>
     <drawable>QOlxHTA_0x799A41A2</drawable>
     <albedo>wXAGiUA_0x6415DE68</albedo>
     <normal>OhZVAYA_0xB9AF1EC5</normal>
     <material>rPhVwCA_0x1663F9CE</material>
     <palette />
     <tint0 value="0" />
     <tint1 value="0" />
     <tint2 value="0" />
     <probability value="255" />
    </Item>
    <Item>
     <drawable>RMFUvJA_0x4B8F1BF6</drawable>
     <albedo>YgpkJlA_0x7480EBA5</albedo>
     <normal>egoQWKA_0xEF1656DA</normal>
     <material>vhPnvMA_0xB3581CC7</material>
     <palette />
     <tint0 value="0" />
     <tint1 value="0" />
     <tint2 value="0" />
     <probability value="255" />
    </Item>
   </explicitAssets>
   <expressions itemType="MetaPedExpression">
    <Item>
     <id value="16009" />
     <value value="-0.1" />
    </Item>
    <Item>
     <id value="38169" />
     <value value="-0.87" />
    </Item>
    <Item>
     <id value="9586" />
     <value value="-0.4" />
    </Item>
   </expressions>
   <subOutfits />
   <variations />
   <tags>
    <Item>DuEerZA_0x92C43393</Item>
    <Item>hTzmBfA_0x4BFA4A07</Item>
    <Item>rRHQlJA_0x2F9EEF6E</Item>
   </tags>
   <shopItems />
  </Item>
  <Item>
   <name>YsEtIdA_0x3EB5190A</name>
   <ethnicity>caucasian</ethnicity>
   <slodDwd>MKzClGA_0x5DB807E3</slodDwd>
   <voiceGroup />
   <damagePack />
   <goreType />
   <scale value="1" />
   <cutsceneScale value="0" />
   <scaleRandomOffset value="0" />
   <coatShine value="0" />
   <coatShineBase value="0" />
   <coatShineMin value="0" />
   <coatShineMax value="1" />
   <eyeRedness value="0" />
   <removeLimbBone>ID_INVALID</removeLimbBone>
   <fullOutfit value="True" />
   <priorityLoad value="False" />
   <preStream value="False" />
   <assets />
   <explicitAssets itemType="MetaPedDefExplicitAsset">
    <Item>
     <drawable>HHKUMEA_0x7D8435A8</drawable>
     <albedo>mRuWHEA_0x2CEC7FFB</albedo>
     <normal>vVTUFEA_0x3752B4EC</normal>
     <material>GnIFkEA_0x56DB20E8</material>
     <palette />
     <tint0 value="0" />
     <tint1 value="0" />
     <tint2 value="0" />
     <probability value="255" />
    </Item>
    <Item>
     <drawable>cs_abigailroberts_fs1_coat_000</drawable>
     <albedo>FBZgKAA_0x3D219C8B</albedo>
     <normal>SYkFaeA_0x16CE2B0A</normal>
     <material>cdssMLA_0x3389B5DB</material>
     <palette />
     <tint0 value="0" />
     <tint1 value="0" />
     <tint2 value="0" />
     <probability value="255" />
    </Item>
    <Item>
     <drawable>KlCXtIA_0x30907A5A</drawable>
     <albedo>eye_cap_gen_0000_c0_000_ab</albedo>
     <normal>eye_cap_gen_0000_c0_000_nm</normal>
     <material>eye_cap_gen_0000_c0_000_m</material>
     <palette />
     <tint0 value="0" />
     <tint1 value="0" />
     <tint2 value="0" />
     <probability value="255" />
    </Item>
    <Item>
     <drawable>smMlOEA_0x251F0702</drawable>
     <albedo>hkYtMLA_0xC7F189E5</albedo>
     <normal>YGeZHQA_0x4147A218</normal>
     <material>ZDcsoDA_0xCF772381</material>
     <palette />
     <tint0 value="0" />
     <tint1 value="0" />
     <tint2 value="0" />
     <probability value="255" />
    </Item>
    <Item>
     <drawable>mJZjigA_0x03E1C1F7</drawable>
     <albedo>ZXPYkCA_0x41A45058</albedo>
     <normal>eyes_gen_0000_c0_000_nm</normal>
     <material>eyes_gen_0000_c0_000_m</material>
     <palette />
     <tint0 value="0" />
     <tint1 value="0" />
     <tint2 value="0" />
     <probability value="255" />
    </Item>
    <Item>
     <drawable>piZdQOA_0xDE517D9E</drawable>
     <albedo>hair_gen_999_c0_999_ab</albedo>
     <normal>hair_gen_999_c0_999_nm</normal>
     <material>hair_gen_999_c0_999_m</material>
     <palette>gCrTlMA_0xDFB1F64C</palette>
     <tint0 value="8" />
     <tint1 value="250" />
     <tint2 value="135" />
     <probability value="255" />
    </Item>
    <Item>
     <drawable>KHTsMKA_0x24496A6D</drawable>
     <albedo>WkAfpPA_0xC03F9101</albedo>
     <normal>JTCFcPA_0x6C35A841</normal>
     <material>APyTsUA_0x1BE249F0</material>
     <palette />
     <tint0 value="0" />
     <tint1 value="0" />
     <tint2 value="0" />
     <probability value="255" />
    </Item>
    <Item>
     <drawable>ylsILtA_0xF3253A77</drawable>
     <albedo>XBZEyHA_0x2D77CC6A</albedo>
     <normal>WSLhjNA_0x3C99B8E6</normal>
     <material>FkJmxKA_0x17BA170C</material>
     <palette />
     <tint0 value="0" />
     <tint1 value="0" />
     <tint2 value="0" />
     <probability value="255" />
    </Item>
    <Item>
     <drawable>WzwETBA_0x924628E1</drawable>
     <albedo>aqymsAA_0x1807B236</albedo>
     <normal>WRQyOMA_0x5B8EA163</normal>
     <material>EolrqGA_0x9F30938C</material>
     <palette />
     <tint0 value="255" />
     <tint1 value="255" />
     <tint2 value="255" />
     <probability value="255" />
    </Item>
    <Item>
     <drawable>QJAYuCA_0x5EB38BD5</drawable>
     <albedo>lCTChFA_0xDC84CE3C</albedo>
     <normal>tGSbxKA_0x4F41899B</normal>
     <material>YrhKeUA_0xA8109BFB</material>
     <palette />
     <tint0 value="255" />
     <tint1 value="255" />
     <tint2 value="255" />
     <probability value="255" />
    </Item>
    <Item>
     <drawable>RMFUvJA_0x4B8F1BF6</drawable>
     <albedo>YgpkJlA_0x7480EBA5</albedo>
     <normal>egoQWKA_0xEF1656DA</normal>
     <material>vhPnvMA_0xB3581CC7</material>
     <palette />
     <tint0 value="0" />
     <tint1 value="0" />
     <tint2 value="0" />
     <probability value="255" />
    </Item>
   </explicitAssets>
   <expressions itemType="MetaPedExpression">
    <Item>
     <id value="16009" />
     <value value="-0.1" />
    </Item>
    <Item>
     <id value="38169" />
     <value value="-0.87" />
    </Item>
    <Item>
     <id value="9586" />
     <value value="-0.4" />
    </Item>
   </expressions>
   <subOutfits />
   <variations />
   <tags>
    <Item>DuEerZA_0x92C43393</Item>
    <Item>hTzmBfA_0x4BFA4A07</Item>
    <Item>rRHQlJA_0x2F9EEF6E</Item>
   </tags>
   <shopItems />
  </Item>
  <Item>
   <name>meta_outfit_default</name>
   <ethnicity>caucasian</ethnicity>
   <slodDwd>HjLqXMA_0x15D8C95A</slodDwd>
   <voiceGroup />
   <damagePack />
   <goreType />
   <scale value="0" />
   <cutsceneScale value="0" />
   <scaleRandomOffset value="0" />
   <coatShine value="0" />
   <coatShineBase value="0" />
   <coatShineMin value="0" />
   <coatShineMax value="1" />
   <eyeRedness value="0" />
   <removeLimbBone>ID_INVALID</removeLimbBone>
   <fullOutfit value="True" />
   <priorityLoad value="False" />
   <preStream value="False" />
   <assets />
   <explicitAssets itemType="MetaPedDefExplicitAsset">
    <Item>
     <drawable>HHKUMEA_0x7D8435A8</drawable>
     <albedo>mRuWHEA_0x2CEC7FFB</albedo>
     <normal>vVTUFEA_0x3752B4EC</normal>
     <material>GnIFkEA_0x56DB20E8</material>
     <palette />
     <tint0 value="0" />
     <tint1 value="0" />
     <tint2 value="0" />
     <probability value="255" />
    </Item>
    <Item>
     <drawable>KlCXtIA_0x30907A5A</drawable>
     <albedo>eye_cap_gen_0000_c0_000_ab</albedo>
     <normal>eye_cap_gen_0000_c0_000_nm</normal>
     <material>eye_cap_gen_0000_c0_000_m</material>
     <palette />
     <tint0 value="0" />
     <tint1 value="0" />
     <tint2 value="0" />
     <probability value="255" />
    </Item>
    <Item>
     <drawable>smMlOEA_0x251F0702</drawable>
     <albedo>hkYtMLA_0xC7F189E5</albedo>
     <normal>YGeZHQA_0x4147A218</normal>
     <material>ZDcsoDA_0xCF772381</material>
     <palette />
     <tint0 value="0" />
     <tint1 value="0" />
     <tint2 value="0" />
     <probability value="255" />
    </Item>
    <Item>
     <drawable>mJZjigA_0x03E1C1F7</drawable>
     <albedo>ZXPYkCA_0x41A45058</albedo>
     <normal>eyes_gen_0000_c0_000_nm</normal>
     <material>eyes_gen_0000_c0_000_m</material>
     <palette />
     <tint0 value="0" />
     <tint1 value="0" />
     <tint2 value="0" />
     <probability value="255" />
    </Item>
    <Item>
     <drawable>BbXwIgA_0xEE399D66</drawable>
     <albedo>hair_gen_999_c0_999_ab</albedo>
     <normal>hair_gen_999_c0_999_nm</normal>
     <material>hair_gen_999_c0_999_m</material>
     <palette>gCrTlMA_0xDFB1F64C</palette>
     <tint0 value="8" />
     <tint1 value="250" />
     <tint2 value="135" />
     <probability value="255" />
    </Item>
    <Item>
     <drawable>KHTsMKA_0x24496A6D</drawable>
     <albedo>WkAfpPA_0xC03F9101</albedo>
     <normal>JTCFcPA_0x6C35A841</normal>
     <material>APyTsUA_0x1BE249F0</material>
     <palette />
     <tint0 value="0" />
     <tint1 value="0" />
     <tint2 value="0" />
     <probability value="255" />
    </Item>
    <Item>
     <drawable>qboNbXA_0x78BAC5A4</drawable>
     <albedo>XBZEyHA_0x2D77CC6A</albedo>
     <normal>WSLhjNA_0x3C99B8E6</normal>
     <material>FkJmxKA_0x17BA170C</material>
     <palette />
     <tint0 value="0" />
     <tint1 value="0" />
     <tint2 value="0" />
     <probability value="255" />
    </Item>
    <Item>
     <drawable>TbITnDA_0x2EE5621D</drawable>
     <albedo>dsXYVMA_0xB23FA248</albedo>
     <normal>qQfjyKA_0xAA7A067D</normal>
     <material>ZNhsZdA_0x5F96AC1E</material>
     <palette />
     <tint0 value="0" />
     <tint1 value="0" />
     <tint2 value="0" />
     <probability value="255" />
    </Item>
    <Item>
     <drawable>QOlxHTA_0x799A41A2</drawable>
     <albedo>wXAGiUA_0x6415DE68</albedo>
     <normal>OhZVAYA_0xB9AF1EC5</normal>
     <material>rPhVwCA_0x1663F9CE</material>
     <palette />
     <tint0 value="0" />
     <tint1 value="0" />
     <tint2 value="0" />
     <probability value="255" />
    </Item>
    <Item>
     <drawable>RMFUvJA_0x4B8F1BF6</drawable>
     <albedo>YgpkJlA_0x7480EBA5</albedo>
     <normal>egoQWKA_0xEF1656DA</normal>
     <material>vhPnvMA_0xB3581CC7</material>
     <palette />
     <tint0 value="0" />
     <tint1 value="0" />
     <tint2 value="0" />
     <probability value="255" />
    </Item>
   </explicitAssets>
   <expressions itemType="MetaPedExpression">
    <Item>
     <id value="16009" />
     <value value="-0.1" />
    </Item>
    <Item>
     <id value="38169" />
     <value value="-0.87" />
    </Item>
    <Item>
     <id value="9586" />
     <value value="-0.4" />
    </Item>
   </expressions>
   <subOutfits />
   <variations />
   <tags>
    <Item>DuEerZA_0x92C43393</Item>
    <Item>hTzmBfA_0x4BFA4A07</Item>
    <Item>rRHQlJA_0x2F9EEF6E</Item>
   </tags>
   <shopItems />
  </Item>
  <Item>
   <name>MYamHQA_0x64BA68C8</name>
   <ethnicity>caucasian</ethnicity>
   <slodDwd>HjLqXMA_0x15D8C95A</slodDwd>
   <voiceGroup />
   <damagePack />
   <goreType />
   <scale value="0" />
   <cutsceneScale value="0" />
   <scaleRandomOffset value="0" />
   <coatShine value="0" />
   <coatShineBase value="0" />
   <coatShineMin value="0" />
   <coatShineMax value="1" />
   <eyeRedness value="0" />
   <removeLimbBone>ID_INVALID</removeLimbBone>
   <fullOutfit value="True" />
   <priorityLoad value="False" />
   <preStream value="False" />
   <assets />
   <explicitAssets itemType="MetaPedDefExplicitAsset">
    <Item>
     <drawable>cs_abigailroberts_fs1_belt_004</drawable>
     <albedo>TWKFCSA_0xD621A764</albedo>
     <normal>WVBqxEA_0x521000CF</normal>
     <material>dCPdpAA_0x85992800</material>
     <palette />
     <tint0 value="255" />
     <tint1 value="255" />
     <tint2 value="255" />
     <probability value="255" />
    </Item>
    <Item>
     <drawable>HHKUMEA_0x7D8435A8</drawable>
     <albedo>mRuWHEA_0x2CEC7FFB</albedo>
     <normal>vVTUFEA_0x3752B4EC</normal>
     <material>GnIFkEA_0x56DB20E8</material>
     <palette />
     <tint0 value="0" />
     <tint1 value="0" />
     <tint2 value="0" />
     <probability value="255" />
    </Item>
    <Item>
     <drawable>KlCXtIA_0x30907A5A</drawable>
     <albedo>eye_cap_gen_0000_c0_000_ab</albedo>
     <normal>eye_cap_gen_0000_c0_000_nm</normal>
     <material>eye_cap_gen_0000_c0_000_m</material>
     <palette />
     <tint0 value="0" />
     <tint1 value="0" />
     <tint2 value="0" />
     <probability value="255" />
    </Item>
    <Item>
     <drawable>smMlOEA_0x251F0702</drawable>
     <albedo>hkYtMLA_0xC7F189E5</albedo>
     <normal>YGeZHQA_0x4147A218</normal>
     <material>ZDcsoDA_0xCF772381</material>
     <palette />
     <tint0 value="0" />
     <tint1 value="0" />
     <tint2 value="0" />
     <probability value="255" />
    </Item>
    <Item>
     <drawable>mJZjigA_0x03E1C1F7</drawable>
     <albedo>ZXPYkCA_0x41A45058</albedo>
     <normal>eyes_gen_0000_c0_000_nm</normal>
     <material>eyes_gen_0000_c0_000_m</material>
     <palette />
     <tint0 value="0" />
     <tint1 value="0" />
     <tint2 value="0" />
     <probability value="255" />
    </Item>
    <Item>
     <drawable>BbXwIgA_0xEE399D66</drawable>
     <albedo>hair_gen_999_c0_999_ab</albedo>
     <normal>hair_gen_999_c0_999_nm</normal>
     <material>hair_gen_999_c0_999_m</material>
     <palette>gCrTlMA_0xDFB1F64C</palette>
     <tint0 value="8" />
     <tint1 value="250" />
     <tint2 value="135" />
     <probability value="255" />
    </Item>
    <Item>
     <drawable>KHTsMKA_0x24496A6D</drawable>
     <albedo>WkAfpPA_0xC03F9101</albedo>
     <normal>JTCFcPA_0x6C35A841</normal>
     <material>APyTsUA_0x1BE249F0</material>
     <palette />
     <tint0 value="0" />
     <tint1 value="0" />
     <tint2 value="0" />
     <probability value="255" />
    </Item>
    <Item>
     <drawable>zcdoAAA_0x8A74E918</drawable>
     <albedo>XBZEyHA_0x2D77CC6A</albedo>
     <normal>WSLhjNA_0x3C99B8E6</normal>
     <material>FkJmxKA_0x17BA170C</material>
     <palette />
     <tint0 value="255" />
     <tint1 value="255" />
     <tint2 value="255" />
     <probability value="255" />
    </Item>
    <Item>
     <drawable>ydFyfEA_0x05D40FFB</drawable>
     <albedo>QCVYacA_0x64A87F6E</albedo>
     <normal>qLOZQCA_0xDFD24294</normal>
     <material>sscfwFA_0xCCAD9131</material>
     <palette />
     <tint0 value="255" />
     <tint1 value="255" />
     <tint2 value="255" />
     <probability value="255" />
    </Item>
    <Item>
     <drawable>QOlxHTA_0x799A41A2</drawable>
     <albedo>QJtDIDA_0x3D1CCC3A</albedo>
     <normal>OhZVAYA_0xB9AF1EC5</normal>
     <material>rPhVwCA_0x1663F9CE</material>
     <palette />
     <tint0 value="0" />
     <tint1 value="0" />
     <tint2 value="0" />
     <probability value="255" />
    </Item>
    <Item>
     <drawable>RMFUvJA_0x4B8F1BF6</drawable>
     <albedo>YgpkJlA_0x7480EBA5</albedo>
     <normal>egoQWKA_0xEF1656DA</normal>
     <material>vhPnvMA_0xB3581CC7</material>
     <palette />
     <tint0 value="0" />
     <tint1 value="0" />
     <tint2 value="0" />
     <probability value="255" />
    </Item>
   </explicitAssets>
   <expressions itemType="MetaPedExpression">
    <Item>
     <id value="16009" />
     <value value="-0.1" />
    </Item>
    <Item>
     <id value="38169" />
     <value value="-0.87" />
    </Item>
    <Item>
     <id value="9586" />
     <value value="-0.4" />
    </Item>
   </expressions>
   <subOutfits />
   <variations />
   <tags>
    <Item>DuEerZA_0x92C43393</Item>
    <Item>hTzmBfA_0x4BFA4A07</Item>
    <Item>rRHQlJA_0x2F9EEF6E</Item>
   </tags>
   <shopItems />
  </Item>
  <Item>
   <name>AGHfpGA_0x4E08EC81</name>
   <ethnicity />
   <slodDwd>MKzClGA_0x5DB807E3</slodDwd>
   <voiceGroup />
   <damagePack />
   <goreType />
   <scale value="0" />
   <cutsceneScale value="0" />
   <scaleRandomOffset value="0" />
   <coatShine value="0" />
   <coatShineBase value="0" />
   <coatShineMin value="0" />
   <coatShineMax value="1" />
   <eyeRedness value="0" />
   <removeLimbBone>ID_INVALID</removeLimbBone>
   <fullOutfit value="True" />
   <priorityLoad value="False" />
   <preStream value="False" />
   <assets />
   <explicitAssets itemType="MetaPedDefExplicitAsset">
    <Item>
     <drawable>ygoRvBA_0x23A5C8B3</drawable>
     <albedo>osIMWHA_0x995283BA</albedo>
     <normal>RVAlkVA_0x4DF74FC5</normal>
     <material>oUNmgXA_0xA79AF3EB</material>
     <palette />
     <tint0 value="255" />
     <tint1 value="255" />
     <tint2 value="255" />
     <probability value="255" />
    </Item>
    <Item>
     <drawable>HHKUMEA_0x7D8435A8</drawable>
     <albedo>mRuWHEA_0x2CEC7FFB</albedo>
     <normal>vVTUFEA_0x3752B4EC</normal>
     <material>GnIFkEA_0x56DB20E8</material>
     <palette />
     <tint0 value="255" />
     <tint1 value="255" />
     <tint2 value="255" />
     <probability value="255" />
    </Item>
    <Item>
     <drawable>KlCXtIA_0x30907A5A</drawable>
     <albedo>eye_cap_gen_0000_c0_000_ab</albedo>
     <normal>eye_cap_gen_0000_c0_000_nm</normal>
     <material>eye_cap_gen_0000_c0_000_m</material>
     <palette />
     <tint0 value="255" />
     <tint1 value="255" />
     <tint2 value="255" />
     <probability value="255" />
    </Item>
    <Item>
     <drawable>smMlOEA_0x251F0702</drawable>
     <albedo>hkYtMLA_0xC7F189E5</albedo>
     <normal>YGeZHQA_0x4147A218</normal>
     <material>ZDcsoDA_0xCF772381</material>
     <palette />
     <tint0 value="255" />
     <tint1 value="255" />
     <tint2 value="255" />
     <probability value="255" />
    </Item>
    <Item>
     <drawable>mJZjigA_0x03E1C1F7</drawable>
     <albedo>ZXPYkCA_0x41A45058</albedo>
     <normal>eyes_gen_0000_c0_000_nm</normal>
     <material>eyes_gen_0000_c0_000_m</material>
     <palette />
     <tint0 value="255" />
     <tint1 value="255" />
     <tint2 value="255" />
     <probability value="255" />
    </Item>
    <Item>
     <drawable>BbXwIgA_0xEE399D66</drawable>
     <albedo>hair_gen_999_c0_999_ab</albedo>
     <normal>hair_gen_999_c0_999_nm</normal>
     <material>hair_gen_999_c0_999_m</material>
     <palette>gCrTlMA_0xDFB1F64C</palette>
     <tint0 value="8" />
     <tint1 value="250" />
     <tint2 value="135" />
     <probability value="255" />
    </Item>
    <Item>
     <drawable>KHTsMKA_0x24496A6D</drawable>
     <albedo>WkAfpPA_0xC03F9101</albedo>
     <normal>JTCFcPA_0x6C35A841</normal>
     <material>APyTsUA_0x1BE249F0</material>
     <palette />
     <tint0 value="255" />
     <tint1 value="255" />
     <tint2 value="255" />
     <probability value="255" />
    </Item>
    <Item>
     <drawable>zcdoAAA_0x8A74E918</drawable>
     <albedo>XBZEyHA_0x2D77CC6A</albedo>
     <normal>WSLhjNA_0x3C99B8E6</normal>
     <material>FkJmxKA_0x17BA170C</material>
     <palette />
     <tint0 value="255" />
     <tint1 value="255" />
     <tint2 value="255" />
     <probability value="255" />
    </Item>
    <Item>
     <drawable>NrUkjcA_0xF5CEAA3B</drawable>
     <albedo>UvLWPCA_0xB169E168</albedo>
     <normal>XhvyEZA_0x7A4566E4</normal>
     <material>fUcMRJA_0x73286808</material>
     <palette />
     <tint0 value="255" />
     <tint1 value="255" />
     <tint2 value="255" />
     <probability value="255" />
    </Item>
    <Item>
     <drawable>ydFyfEA_0x05D40FFB</drawable>
     <albedo>QCVYacA_0x64A87F6E</albedo>
     <normal>qLOZQCA_0xDFD24294</normal>
     <material>sscfwFA_0xCCAD9131</material>
     <palette />
     <tint0 value="255" />
     <tint1 value="255" />
     <tint2 value="255" />
     <probability value="255" />
    </Item>
    <Item>
     <drawable>QOlxHTA_0x799A41A2</drawable>
     <albedo>QJtDIDA_0x3D1CCC3A</albedo>
     <normal>OhZVAYA_0xB9AF1EC5</normal>
     <material>rPhVwCA_0x1663F9CE</material>
     <palette />
     <tint0 value="255" />
     <tint1 value="255" />
     <tint2 value="255" />
     <probability value="255" />
    </Item>
    <Item>
     <drawable>RMFUvJA_0x4B8F1BF6</drawable>
     <albedo>YgpkJlA_0x7480EBA5</albedo>
     <normal>egoQWKA_0xEF1656DA</normal>
     <material>vhPnvMA_0xB3581CC7</material>
     <palette />
     <tint0 value="255" />
     <tint1 value="255" />
     <tint2 value="255" />
     <probability value="255" />
    </Item>
   </explicitAssets>
   <expressions />
   <subOutfits />
   <variations />
   <tags>
    <Item>DuEerZA_0x92C43393</Item>
    <Item>hTzmBfA_0x4BFA4A07</Item>
    <Item>rRHQlJA_0x2F9EEF6E</Item>
   </tags>
   <shopItems />
  </Item>
  <Item>
   <name>cTXBdAA_0x37BBF635</name>
   <ethnicity>caucasian</ethnicity>
   <slodDwd>HjLqXMA_0x15D8C95A</slodDwd>
   <voiceGroup />
   <damagePack />
   <goreType />
   <scale value="1" />
   <cutsceneScale value="0" />
   <scaleRandomOffset value="0" />
   <coatShine value="0" />
   <coatShineBase value="0" />
   <coatShineMin value="0" />
   <coatShineMax value="1" />
   <eyeRedness value="0" />
   <removeLimbBone>ID_INVALID</removeLimbBone>
   <fullOutfit value="True" />
   <priorityLoad value="False" />
   <preStream value="False" />
   <assets />
   <explicitAssets itemType="MetaPedDefExplicitAsset">
    <Item>
     <drawable>SVnGoPA_0x626B3BE1</drawable>
     <albedo>AeWtHBA_0x1A3077AF</albedo>
     <normal>sFgDmfA_0x6A6588DC</normal>
     <material>vzgThGA_0x67ADBE16</material>
     <palette />
     <tint0 value="0" />
     <tint1 value="0" />
     <tint2 value="0" />
     <probability value="255" />
    </Item>
    <Item>
     <drawable>HHKUMEA_0x7D8435A8</drawable>
     <albedo>mRuWHEA_0x2CEC7FFB</albedo>
     <normal>vVTUFEA_0x3752B4EC</normal>
     <material>GnIFkEA_0x56DB20E8</material>
     <palette />
     <tint0 value="0" />
     <tint1 value="0" />
     <tint2 value="0" />
     <probability value="255" />
    </Item>
    <Item>
     <drawable>KlCXtIA_0x30907A5A</drawable>
     <albedo>eye_cap_gen_0000_c0_000_ab</albedo>
     <normal>eye_cap_gen_0000_c0_000_nm</normal>
     <material>eye_cap_gen_0000_c0_000_m</material>
     <palette />
     <tint0 value="0" />
     <tint1 value="0" />
     <tint2 value="0" />
     <probability value="255" />
    </Item>
    <Item>
     <drawable>smMlOEA_0x251F0702</drawable>
     <albedo>hkYtMLA_0xC7F189E5</albedo>
     <normal>YGeZHQA_0x4147A218</normal>
     <material>ZDcsoDA_0xCF772381</material>
     <palette />
     <tint0 value="0" />
     <tint1 value="0" />
     <tint2 value="0" />
     <probability value="255" />
    </Item>
    <Item>
     <drawable>mJZjigA_0x03E1C1F7</drawable>
     <albedo>ZXPYkCA_0x41A45058</albedo>
     <normal>eyes_gen_0000_c0_000_nm</normal>
     <material>eyes_gen_0000_c0_000_m</material>
     <palette />
     <tint0 value="0" />
     <tint1 value="0" />
     <tint2 value="0" />
     <probability value="255" />
    </Item>
    <Item>
     <drawable>XZtRvEA_0x09A5543D</drawable>
     <albedo>hair_gen_999_c0_999_ab</albedo>
     <normal>hair_gen_999_c0_999_nm</normal>
     <material>hair_gen_999_c0_999_m</material>
     <palette>gCrTlMA_0xDFB1F64C</palette>
     <tint0 value="8" />
     <tint1 value="250" />
     <tint2 value="135" />
     <probability value="255" />
    </Item>
    <Item>
     <drawable>KHTsMKA_0x24496A6D</drawable>
     <albedo>WkAfpPA_0xC03F9101</albedo>
     <normal>JTCFcPA_0x6C35A841</normal>
     <material>APyTsUA_0x1BE249F0</material>
     <palette />
     <tint0 value="0" />
     <tint1 value="0" />
     <tint2 value="0" />
     <probability value="255" />
    </Item>
    <Item>
     <drawable>mqXDMGA_0xCCE6D86C</drawable>
     <albedo>aZDJkAA_0x276AA32A</albedo>
     <normal>BmPThPA_0x988FF133</normal>
     <material>qRJeTBA_0xB0F82075</material>
     <palette />
     <tint0 value="0" />
     <tint1 value="0" />
     <tint2 value="0" />
     <probability value="255" />
    </Item>
    <Item>
     <drawable>deeYADA_0x68E75624</drawable>
     <albedo>MFeIWjA_0x3C9CBEFE</albedo>
     <normal>csFxGlA_0xF49BE732</normal>
     <material>rfvylnA_0xB725A61D</material>
     <palette />
     <tint0 value="0" />
     <tint1 value="0" />
     <tint2 value="0" />
     <probability value="255" />
    </Item>
    <Item>
     <drawable>QJAYuCA_0x5EB38BD5</drawable>
     <albedo>xathgjA_0x8871A591</albedo>
     <normal>tGSbxKA_0x4F41899B</normal>
     <material>YrhKeUA_0xA8109BFB</material>
     <palette />
     <tint0 value="255" />
     <tint1 value="255" />
     <tint2 value="255" />
     <probability value="255" />
    </Item>
    <Item>
     <drawable>RMFUvJA_0x4B8F1BF6</drawable>
     <albedo>YgpkJlA_0x7480EBA5</albedo>
     <normal>egoQWKA_0xEF1656DA</normal>
     <material>vhPnvMA_0xB3581CC7</material>
     <palette />
     <tint0 value="0" />
     <tint1 value="0" />
     <tint2 value="0" />
     <probability value="255" />
    </Item>
    <Item>
     <drawable>ylsILtA_0xF3253A77</drawable>
     <albedo>XBZEyHA_0x2D77CC6A</albedo>
     <normal>hand_fr1_000_c0_000_nm</normal>
     <material>hand_fr1_000_c0_000_m</material>
     <palette />
     <tint0 value="0" />
     <tint1 value="0" />
     <tint2 value="0" />
     <probability value="255" />
    </Item>
   </explicitAssets>
   <expressions itemType="MetaPedExpression">
    <Item>
     <id value="38169" />
     <value value="-1" />
    </Item>
    <Item>
     <id value="16009" />
     <value value="-0.3" />
    </Item>
    <Item>
     <id value="9586" />
     <value value="-0.1" />
    </Item>
   </expressions>
   <subOutfits />
   <variations />
   <tags>
    <Item>DuEerZA_0x92C43393</Item>
    <Item>hTzmBfA_0x4BFA4A07</Item>
    <Item>rRHQlJA_0x2F9EEF6E</Item>
   </tags>
   <shopItems />
  </Item>
  <Item>
   <name>FccvbyA_0x06CFA8BB</name>
   <ethnicity>caucasian</ethnicity>
   <slodDwd>rEAvnHA_0xC5DB9E33</slodDwd>
   <voiceGroup />
   <damagePack />
   <goreType />
   <scale value="0" />
   <cutsceneScale value="0" />
   <scaleRandomOffset value="0" />
   <coatShine value="0" />
   <coatShineBase value="0" />
   <coatShineMin value="0" />
   <coatShineMax value="1" />
   <eyeRedness value="0" />
   <removeLimbBone>ID_INVALID</removeLimbBone>
   <fullOutfit value="True" />
   <priorityLoad value="False" />
   <preStream value="False" />
   <assets />
   <explicitAssets itemType="MetaPedDefExplicitAsset">
    <Item>
     <drawable>HHKUMEA_0x7D8435A8</drawable>
     <albedo>mRuWHEA_0x2CEC7FFB</albedo>
     <normal>vVTUFEA_0x3752B4EC</normal>
     <material>GnIFkEA_0x56DB20E8</material>
     <palette />
     <tint0 value="0" />
     <tint1 value="0" />
     <tint2 value="0" />
     <probability value="255" />
    </Item>
    <Item>
     <drawable>KlCXtIA_0x30907A5A</drawable>
     <albedo>eye_cap_gen_0000_c0_000_ab</albedo>
     <normal>eye_cap_gen_0000_c0_000_nm</normal>
     <material>eye_cap_gen_0000_c0_000_m</material>
     <palette />
     <tint0 value="0" />
     <tint1 value="0" />
     <tint2 value="0" />
     <probability value="255" />
    </Item>
    <Item>
     <drawable>smMlOEA_0x251F0702</drawable>
     <albedo>hkYtMLA_0xC7F189E5</albedo>
     <normal>YGeZHQA_0x4147A218</normal>
     <material>ZDcsoDA_0xCF772381</material>
     <palette />
     <tint0 value="0" />
     <tint1 value="0" />
     <tint2 value="0" />
     <probability value="255" />
    </Item>
    <Item>
     <drawable>mJZjigA_0x03E1C1F7</drawable>
     <albedo>ZXPYkCA_0x41A45058</albedo>
     <normal>eyes_gen_0000_c0_000_nm</normal>
     <material>eyes_gen_0000_c0_000_m</material>
     <palette />
     <tint0 value="0" />
     <tint1 value="0" />
     <tint2 value="0" />
     <probability value="255" />
    </Item>
    <Item>
     <drawable>mBxoGAA_0x24D490EC</drawable>
     <albedo>CyvVTGA_0xE6E33463</albedo>
     <normal>ehokHCA_0xB7E96390</normal>
     <material>rJVlELA_0xC4CDE225</material>
     <palette />
     <tint0 value="255" />
     <tint1 value="255" />
     <tint2 value="255" />
     <probability value="255" />
    </Item>
    <Item>
     <drawable>XZtRvEA_0x09A5543D</drawable>
     <albedo>hair_gen_999_c0_999_ab</albedo>
     <normal>hair_gen_999_c0_999_nm</normal>
     <material>hair_gen_999_c0_999_m</material>
     <palette>gCrTlMA_0xDFB1F64C</palette>
     <tint0 value="8" />
     <tint1 value="250" />
     <tint2 value="135" />
     <probability value="255" />
    </Item>
    <Item>
     <drawable>ErKCfSA_0xB9A7A37B</drawable>
     <albedo>UDfrJHA_0xEAA7614C</albedo>
     <normal>XgwLoQA_0x1C0ABC3E</normal>
     <material>XDzbkMA_0x6A19F24D</material>
     <palette />
     <tint0 value="255" />
     <tint1 value="255" />
     <tint2 value="255" />
     <probability value="255" />
    </Item>
    <Item>
     <drawable>KHTsMKA_0x24496A6D</drawable>
     <albedo>WkAfpPA_0xC03F9101</albedo>
     <normal>JTCFcPA_0x6C35A841</normal>
     <material>APyTsUA_0x1BE249F0</material>
     <palette />
     <tint0 value="0" />
     <tint1 value="0" />
     <tint2 value="0" />
     <probability value="255" />
    </Item>
    <Item>
     <drawable>OSVWlXA_0xC5CA29B8</drawable>
     <albedo>iYvmaCA_0xD18C031F</albedo>
     <normal>GFofRDA_0x8E09256E</normal>
     <material>qNjhTEA_0x76B8C644</material>
     <palette />
     <tint0 value="255" />
     <tint1 value="255" />
     <tint2 value="255" />
     <probability value="255" />
    </Item>
    <Item>
     <drawable>UwODbDA_0xE861D517</drawable>
     <albedo>AImhmNA_0xE4E0600F</albedo>
     <normal>sYGfdJA_0x49D22C8B</normal>
     <material>XFROTPA_0x980B8183</material>
     <palette />
     <tint0 value="255" />
     <tint1 value="255" />
     <tint2 value="255" />
     <probability value="255" />
    </Item>
    <Item>
     <drawable>lQsCHLA_0x69E4A237</drawable>
     <albedo>cEOPVAA_0xAA637E8F</albedo>
     <normal>LXrNxJA_0x296F2589</normal>
     <material>ldZQFMA_0x50B1DB29</material>
     <palette />
     <tint0 value="255" />
     <tint1 value="255" />
     <tint2 value="255" />
     <probability value="255" />
    </Item>
    <Item>
     <drawable>RMFUvJA_0x4B8F1BF6</drawable>
     <albedo>YgpkJlA_0x7480EBA5</albedo>
     <normal>egoQWKA_0xEF1656DA</normal>
     <material>vhPnvMA_0xB3581CC7</material>
     <palette />
     <tint0 value="0" />
     <tint1 value="0" />
     <tint2 value="0" />
     <probability value="255" />
    </Item>
   </explicitAssets>
   <expressions itemType="MetaPedExpression">
    <Item>
     <id value="16009" />
     <value value="-0.51" />
    </Item>
    <Item>
     <id value="38169" />
     <value value="-0.976" />
    </Item>
    <Item>
     <id value="9586" />
     <value value="-0.4" />
    </Item>
   </expressions>
   <subOutfits />
   <variations />
   <tags>
    <Item>DuEerZA_0x92C43393</Item>
    <Item>hTzmBfA_0x4BFA4A07</Item>
    <Item>rRHQlJA_0x2F9EEF6E</Item>
   </tags>
   <shopItems />
  </Item>
  <Item>
   <name>cqUqEJA_0xD2D8EAA6</name>
   <ethnicity>caucasian</ethnicity>
   <slodDwd>GEGCgGA_0x748EC987</slodDwd>
   <voiceGroup />
   <damagePack />
   <goreType />
   <scale value="1" />
   <cutsceneScale value="0" />
   <scaleRandomOffset value="0" />
   <coatShine value="0" />
   <coatShineBase value="0" />
   <coatShineMin value="0" />
   <coatShineMax value="1" />
   <eyeRedness value="0" />
   <removeLimbBone>ID_INVALID</removeLimbBone>
   <fullOutfit value="True" />
   <priorityLoad value="False" />
   <preStream value="False" />
   <assets />
   <explicitAssets itemType="MetaPedDefExplicitAsset">
    <Item>
     <drawable>KlCXtIA_0x30907A5A</drawable>
     <albedo>eye_cap_gen_0000_c0_000_ab</albedo>
     <normal>eye_cap_gen_0000_c0_000_nm</normal>
     <material>eye_cap_gen_0000_c0_000_m</material>
     <palette />
     <tint0 value="0" />
     <tint1 value="0" />
     <tint2 value="0" />
     <probability value="255" />
    </Item>
    <Item>
     <drawable>smMlOEA_0x251F0702</drawable>
     <albedo>hkYtMLA_0xC7F189E5</albedo>
     <normal>YGeZHQA_0x4147A218</normal>
     <material>ZDcsoDA_0xCF772381</material>
     <palette />
     <tint0 value="0" />
     <tint1 value="0" />
     <tint2 value="0" />
     <probability value="255" />
    </Item>
    <Item>
     <drawable>mJZjigA_0x03E1C1F7</drawable>
     <albedo>ZXPYkCA_0x41A45058</albedo>
     <normal>eyes_gen_0000_c0_000_nm</normal>
     <material>eyes_gen_0000_c0_000_m</material>
     <palette />
     <tint0 value="0" />
     <tint1 value="0" />
     <tint2 value="0" />
     <probability value="255" />
    </Item>
    <Item>
     <drawable>wzmzNQA_0x17D6F0A0</drawable>
     <albedo>hair_gen_999_c0_999_ab</albedo>
     <normal>hair_gen_999_c0_999_nm</normal>
     <material>hair_gen_999_c0_999_m</material>
     <palette>gCrTlMA_0xDFB1F64C</palette>
     <tint0 value="8" />
     <tint1 value="250" />
     <tint2 value="135" />
     <probability value="255" />
    </Item>
    <Item>
     <drawable>KHTsMKA_0x24496A6D</drawable>
     <albedo>WkAfpPA_0xC03F9101</albedo>
     <normal>JTCFcPA_0x6C35A841</normal>
     <material>APyTsUA_0x1BE249F0</material>
     <palette />
     <tint0 value="0" />
     <tint1 value="0" />
     <tint2 value="0" />
     <probability value="255" />
    </Item>
    <Item>
     <drawable>MTtVRCA_0x0F7F3E38</drawable>
     <albedo>nxmjGCA_0x44103E09</albedo>
     <normal>fZftVgA_0x761A2495</normal>
     <material>GYbtKCA_0x460C3642</material>
     <palette />
     <tint0 value="255" />
     <tint1 value="255" />
     <tint2 value="255" />
     <probability value="255" />
    </Item>
    <Item>
     <drawable>zZSopBA_0xAFDE3212</drawable>
     <albedo>zvJdcAA_0x6161DE24</albedo>
     <normal>pIXGgSA_0x87A3A37A</normal>
     <material>eFMdlHA_0x0E129E28</material>
     <palette />
     <tint0 value="255" />
     <tint1 value="255" />
     <tint2 value="255" />
     <probability value="255" />
    </Item>
    <Item>
     <drawable>aOLjqAA_0x0C916D4F</drawable>
     <albedo>XBZEyHA_0x2D77CC6A</albedo>
     <normal>WSLhjNA_0x3C99B8E6</normal>
     <material>FkJmxKA_0x17BA170C</material>
     <palette />
     <tint0 value="255" />
     <tint1 value="255" />
     <tint2 value="255" />
     <probability value="255" />
    </Item>
    <Item>
     <drawable>RMFUvJA_0x4B8F1BF6</drawable>
     <albedo>YgpkJlA_0x7480EBA5</albedo>
     <normal>egoQWKA_0xEF1656DA</normal>
     <material>vhPnvMA_0xB3581CC7</material>
     <palette />
     <tint0 value="0" />
     <tint1 value="0" />
     <tint2 value="0" />
     <probability value="255" />
    </Item>
   </explicitAssets>
   <expressions itemType="MetaPedExpression">
    <Item>
     <id value="16009" />
     <value value="-0.1" />
    </Item>
    <Item>
     <id value="38169" />
     <value value="-0.87" />
    </Item>
    <Item>
     <id value="9586" />
     <value value="-0.4" />
    </Item>
   </expressions>
   <subOutfits />
   <variations />
   <tags>
    <Item>DuEerZA_0x92C43393</Item>
    <Item>hTzmBfA_0x4BFA4A07</Item>
    <Item>rRHQlJA_0x2F9EEF6E</Item>
   </tags>
   <shopItems />
  </Item>
  <Item>
   <name>YkloNLA_0xFA1538C7</name>
   <ethnicity>caucasian</ethnicity>
   <slodDwd>HjLqXMA_0x15D8C95A</slodDwd>
   <voiceGroup />
   <damagePack />
   <goreType />
   <scale value="0" />
   <cutsceneScale value="0" />
   <scaleRandomOffset value="0" />
   <coatShine value="0" />
   <coatShineBase value="0" />
   <coatShineMin value="0" />
   <coatShineMax value="1" />
   <eyeRedness value="0" />
   <removeLimbBone>ID_INVALID</removeLimbBone>
   <fullOutfit value="True" />
   <priorityLoad value="False" />
   <preStream value="False" />
   <assets />
   <explicitAssets itemType="MetaPedDefExplicitAsset">
    <Item>
     <drawable>HHKUMEA_0x7D8435A8</drawable>
     <albedo>mRuWHEA_0x2CEC7FFB</albedo>
     <normal>vVTUFEA_0x3752B4EC</normal>
     <material>GnIFkEA_0x56DB20E8</material>
     <palette />
     <tint0 value="0" />
     <tint1 value="0" />
     <tint2 value="0" />
     <probability value="255" />
    </Item>
    <Item>
     <drawable>KlCXtIA_0x30907A5A</drawable>
     <albedo>eye_cap_gen_0000_c0_000_ab</albedo>
     <normal>eye_cap_gen_0000_c0_000_nm</normal>
     <material>eye_cap_gen_0000_c0_000_m</material>
     <palette />
     <tint0 value="0" />
     <tint1 value="0" />
     <tint2 value="0" />
     <probability value="255" />
    </Item>
    <Item>
     <drawable>smMlOEA_0x251F0702</drawable>
     <albedo>hkYtMLA_0xC7F189E5</albedo>
     <normal>YGeZHQA_0x4147A218</normal>
     <material>ZDcsoDA_0xCF772381</material>
     <palette />
     <tint0 value="0" />
     <tint1 value="0" />
     <tint2 value="0" />
     <probability value="255" />
    </Item>
    <Item>
     <drawable>mJZjigA_0x03E1C1F7</drawable>
     <albedo>ZXPYkCA_0x41A45058</albedo>
     <normal>eyes_gen_0000_c0_000_nm</normal>
     <material>eyes_gen_0000_c0_000_m</material>
     <palette />
     <tint0 value="0" />
     <tint1 value="0" />
     <tint2 value="0" />
     <probability value="255" />
    </Item>
    <Item>
     <drawable>BbXwIgA_0xEE399D66</drawable>
     <albedo>hair_gen_999_c0_999_ab</albedo>
     <normal>hair_gen_999_c0_999_nm</normal>
     <material>hair_gen_999_c0_999_m</material>
     <palette>gCrTlMA_0xDFB1F64C</palette>
     <tint0 value="8" />
     <tint1 value="250" />
     <tint2 value="135" />
     <probability value="255" />
    </Item>
    <Item>
     <drawable>KHTsMKA_0x24496A6D</drawable>
     <albedo>WkAfpPA_0xC03F9101</albedo>
     <normal>JTCFcPA_0x6C35A841</normal>
     <material>APyTsUA_0x1BE249F0</material>
     <palette />
     <tint0 value="0" />
     <tint1 value="0" />
     <tint2 value="0" />
     <probability value="255" />
    </Item>
    <Item>
     <drawable>qboNbXA_0x78BAC5A4</drawable>
     <albedo>XBZEyHA_0x2D77CC6A</albedo>
     <normal>WSLhjNA_0x3C99B8E6</normal>
     <material>FkJmxKA_0x17BA170C</material>
     <palette />
     <tint0 value="0" />
     <tint1 value="0" />
     <tint2 value="0" />
     <probability value="255" />
    </Item>
    <Item>
     <drawable>TbITnDA_0x2EE5621D</drawable>
     <albedo>dsXYVMA_0xB23FA248</albedo>
     <normal>qQfjyKA_0xAA7A067D</normal>
     <material>ZNhsZdA_0x5F96AC1E</material>
     <palette />
     <tint0 value="0" />
     <tint1 value="0" />
     <tint2 value="0" />
     <probability value="255" />
    </Item>
    <Item>
     <drawable>QOlxHTA_0x799A41A2</drawable>
     <albedo>wXAGiUA_0x6415DE68</albedo>
     <normal>OhZVAYA_0xB9AF1EC5</normal>
     <material>rPhVwCA_0x1663F9CE</material>
     <palette />
     <tint0 value="0" />
     <tint1 value="0" />
     <tint2 value="0" />
     <probability value="255" />
    </Item>
    <Item>
     <drawable>RMFUvJA_0x4B8F1BF6</drawable>
     <albedo>YgpkJlA_0x7480EBA5</albedo>
     <normal>egoQWKA_0xEF1656DA</normal>
     <material>vhPnvMA_0xB3581CC7</material>
     <palette />
     <tint0 value="0" />
     <tint1 value="0" />
     <tint2 value="0" />
     <probability value="255" />
    </Item>
   </explicitAssets>
   <expressions itemType="MetaPedExpression">
    <Item>
     <id value="16009" />
     <value value="-0.1" />
    </Item>
    <Item>
     <id value="38169" />
     <value value="-0.87" />
    </Item>
    <Item>
     <id value="9586" />
     <value value="-0.4" />
    </Item>
   </expressions>
   <subOutfits />
   <variations />
   <tags>
    <Item>DuEerZA_0x92C43393</Item>
    <Item>hTzmBfA_0x4BFA4A07</Item>
    <Item>rRHQlJA_0x2F9EEF6E</Item>
   </tags>
   <shopItems />
  </Item>
  <Item>
   <name>oquxkkA_0x1BB5E76A</name>
   <ethnicity>caucasian</ethnicity>
   <slodDwd>HjLqXMA_0x15D8C95A</slodDwd>
   <voiceGroup />
   <damagePack />
   <goreType />
   <scale value="1" />
   <cutsceneScale value="0" />
   <scaleRandomOffset value="0" />
   <coatShine value="0" />
   <coatShineBase value="0" />
   <coatShineMin value="0" />
   <coatShineMax value="1" />
   <eyeRedness value="0" />
   <removeLimbBone>ID_INVALID</removeLimbBone>
   <fullOutfit value="True" />
   <priorityLoad value="False" />
   <preStream value="False" />
   <assets />
   <explicitAssets itemType="MetaPedDefExplicitAsset">
    <Item>
     <drawable>HHKUMEA_0x7D8435A8</drawable>
     <albedo>mRuWHEA_0x2CEC7FFB</albedo>
     <normal>vVTUFEA_0x3752B4EC</normal>
     <material>GnIFkEA_0x56DB20E8</material>
     <palette />
     <tint0 value="0" />
     <tint1 value="0" />
     <tint2 value="0" />
     <probability value="255" />
    </Item>
    <Item>
     <drawable>KlCXtIA_0x30907A5A</drawable>
     <albedo>eye_cap_gen_0000_c0_000_ab</albedo>
     <normal>eye_cap_gen_0000_c0_000_nm</normal>
     <material>eye_cap_gen_0000_c0_000_m</material>
     <palette />
     <tint0 value="0" />
     <tint1 value="0" />
     <tint2 value="0" />
     <probability value="255" />
    </Item>
    <Item>
     <drawable>smMlOEA_0x251F0702</drawable>
     <albedo>hkYtMLA_0xC7F189E5</albedo>
     <normal>YGeZHQA_0x4147A218</normal>
     <material>ZDcsoDA_0xCF772381</material>
     <palette />
     <tint0 value="0" />
     <tint1 value="0" />
     <tint2 value="0" />
     <probability value="255" />
    </Item>
    <Item>
     <drawable>mJZjigA_0x03E1C1F7</drawable>
     <albedo>ZXPYkCA_0x41A45058</albedo>
     <normal>eyes_gen_0000_c0_000_nm</normal>
     <material>eyes_gen_0000_c0_000_m</material>
     <palette />
     <tint0 value="0" />
     <tint1 value="0" />
     <tint2 value="0" />
     <probability value="255" />
    </Item>
    <Item>
     <drawable>eFfQABA_0xEC20193B</drawable>
     <albedo>hair_gen_999_c0_999_ab</albedo>
     <normal>hair_gen_999_c0_999_nm</normal>
     <material>hair_gen_999_c0_999_m</material>
     <palette>gCrTlMA_0xDFB1F64C</palette>
     <tint0 value="8" />
     <tint1 value="250" />
     <tint2 value="135" />
     <probability value="255" />
    </Item>
    <Item>
     <drawable>KHTsMKA_0x24496A6D</drawable>
     <albedo>WkAfpPA_0xC03F9101</albedo>
     <normal>JTCFcPA_0x6C35A841</normal>
     <material>APyTsUA_0x1BE249F0</material>
     <palette />
     <tint0 value="0" />
     <tint1 value="0" />
     <tint2 value="0" />
     <probability value="255" />
    </Item>
    <Item>
     <drawable>JbvztCA_0xCCDC1E0C</drawable>
     <albedo>kXbiDHA_0xA02FADDF</albedo>
     <normal>ZIIqiUA_0x13A53AB0</normal>
     <material>assccRA_0x360C0374</material>
     <palette />
     <tint0 value="255" />
     <tint1 value="255" />
     <tint2 value="255" />
     <probability value="255" />
    </Item>
    <Item>
     <drawable>QJAYuCA_0x5EB38BD5</drawable>
     <albedo>mApunIA_0x78237738</albedo>
     <normal>tGSbxKA_0x4F41899B</normal>
     <material>wteRXBA_0x5AEB1BF9</material>
     <palette />
     <tint0 value="255" />
     <tint1 value="255" />
     <tint2 value="255" />
     <probability value="255" />
    </Item>
    <Item>
     <drawable>RMFUvJA_0x4B8F1BF6</drawable>
     <albedo>YgpkJlA_0x7480EBA5</albedo>
     <normal>egoQWKA_0xEF1656DA</normal>
     <material>vhPnvMA_0xB3581CC7</material>
     <palette />
     <tint0 value="0" />
     <tint1 value="0" />
     <tint2 value="0" />
     <probability value="255" />
    </Item>
    <Item>
     <drawable>ylsILtA_0xF3253A77</drawable>
     <albedo>XBZEyHA_0x2D77CC6A</albedo>
     <normal>hand_fr1_000_c0_000_nm</normal>
     <material>hand_fr1_000_c0_000_m</material>
     <palette />
     <tint0 value="0" />
     <tint1 value="0" />
     <tint2 value="0" />
     <probability value="255" />
    </Item>
   </explicitAssets>
   <expressions itemType="MetaPedExpression">
    <Item>
     <id value="16009" />
     <value value="-0.1" />
    </Item>
    <Item>
     <id value="38169" />
     <value value="-0.87" />
    </Item>
    <Item>
     <id value="9586" />
     <value value="-0.4" />
    </Item>
   </expressions>
   <subOutfits />
   <variations />
   <tags>
    <Item>DuEerZA_0x92C43393</Item>
    <Item>hTzmBfA_0x4BFA4A07</Item>
    <Item>rRHQlJA_0x2F9EEF6E</Item>
   </tags>
   <shopItems />
  </Item>
  <Item>
   <name>BpklEAA_0x79155250</name>
   <ethnicity>caucasian</ethnicity>
   <slodDwd>HjLqXMA_0x15D8C95A</slodDwd>
   <voiceGroup />
   <damagePack />
   <goreType />
   <scale value="1" />
   <cutsceneScale value="0" />
   <scaleRandomOffset value="0" />
   <coatShine value="0" />
   <coatShineBase value="0" />
   <coatShineMin value="0" />
   <coatShineMax value="1" />
   <eyeRedness value="0" />
   <removeLimbBone>ID_INVALID</removeLimbBone>
   <fullOutfit value="True" />
   <priorityLoad value="False" />
   <preStream value="False" />
   <assets />
   <explicitAssets itemType="MetaPedDefExplicitAsset">
    <Item>
     <drawable>cs_abigailroberts_fs1_belt_005</drawable>
     <albedo>cyImhCA_0x4B60EADD</albedo>
     <normal>rFFTDAA_0x1DD3A377</normal>
     <material>hOuYldA_0xD8BF2BEB</material>
     <palette />
     <tint0 value="255" />
     <tint1 value="255" />
     <tint2 value="255" />
     <probability value="255" />
    </Item>
    <Item>
     <drawable>IniAHOA_0xCB4E513B</drawable>
     <albedo>jcQhTEA_0x7BAFACEB</albedo>
     <normal>eFWPnHA_0xD61E3BCE</normal>
     <material>xONNQDA_0x613AB3EF</material>
     <palette />
     <tint0 value="255" />
     <tint1 value="255" />
     <tint2 value="255" />
     <probability value="255" />
    </Item>
    <Item>
     <drawable>yyIpleA_0x485F88DA</drawable>
     <albedo>SsHajIA_0xE375C569</albedo>
     <normal>FYtUwIA_0x74BCC97D</normal>
     <material>kjomxHA_0xA39490B1</material>
     <palette />
     <tint0 value="255" />
     <tint1 value="255" />
     <tint2 value="255" />
     <probability value="255" />
    </Item>
    <Item>
     <drawable>uWmEneA_0x239C5638</drawable>
     <albedo>BfCElNA_0x0C30CB2D</albedo>
     <normal>iYFdrmA_0x4C6D5012</normal>
     <material>BRTxHAA_0x02D01046</material>
     <palette />
     <tint0 value="255" />
     <tint1 value="255" />
     <tint2 value="255" />
     <probability value="255" />
    </Item>
    <Item>
     <drawable>KlCXtIA_0x30907A5A</drawable>
     <albedo>eye_cap_gen_0000_c0_000_ab</albedo>
     <normal>eye_cap_gen_0000_c0_000_nm</normal>
     <material>eye_cap_gen_0000_c0_000_m</material>
     <palette />
     <tint0 value="0" />
     <tint1 value="0" />
     <tint2 value="0" />
     <probability value="255" />
    </Item>
    <Item>
     <drawable>smMlOEA_0x251F0702</drawable>
     <albedo>hkYtMLA_0xC7F189E5</albedo>
     <normal>YGeZHQA_0x4147A218</normal>
     <material>ZDcsoDA_0xCF772381</material>
     <palette />
     <tint0 value="0" />
     <tint1 value="0" />
     <tint2 value="0" />
     <probability value="255" />
    </Item>
    <Item>
     <drawable>mJZjigA_0x03E1C1F7</drawable>
     <albedo>ZXPYkCA_0x41A45058</albedo>
     <normal>eyes_gen_0000_c0_000_nm</normal>
     <material>eyes_gen_0000_c0_000_m</material>
     <palette />
     <tint0 value="0" />
     <tint1 value="0" />
     <tint2 value="0" />
     <probability value="255" />
    </Item>
    <Item>
     <drawable>BbXwIgA_0xEE399D66</drawable>
     <albedo>hair_gen_999_c0_999_ab</albedo>
     <normal>hair_gen_999_c0_999_nm</normal>
     <material>hair_gen_999_c0_999_m</material>
     <palette>gCrTlMA_0xDFB1F64C</palette>
     <tint0 value="8" />
     <tint1 value="250" />
     <tint2 value="135" />
     <probability value="255" />
    </Item>
    <Item>
     <drawable>KHTsMKA_0x24496A6D</drawable>
     <albedo>OxqXyEA_0x25350FD8</albedo>
     <normal>JTCFcPA_0x6C35A841</normal>
     <material>APyTsUA_0x1BE249F0</material>
     <palette />
     <tint0 value="0" />
     <tint1 value="0" />
     <tint2 value="0" />
     <probability value="255" />
    </Item>
    <Item>
     <drawable>rLrqWJA_0xD2AC437C</drawable>
     <albedo>PyTVUVA_0xDBC04AA2</albedo>
     <normal>PqQzZHA_0x3E3D049A</normal>
     <material>bmAKjEA_0xF13D13F3</material>
     <palette />
     <tint0 value="255" />
     <tint1 value="255" />
     <tint2 value="255" />
     <probability value="255" />
    </Item>
    <Item>
     <drawable>asXPlHA_0xE15E16E9</drawable>
     <albedo>XBZEyHA_0x2D77CC6A</albedo>
     <normal>WSLhjNA_0x3C99B8E6</normal>
     <material>FkJmxKA_0x17BA170C</material>
     <palette />
     <tint0 value="255" />
     <tint1 value="255" />
     <tint2 value="255" />
     <probability value="255" />
    </Item>
    <Item>
     <drawable>cs_abigailroberts_fs1_shirt_009</drawable>
     <albedo>TSkCzFA_0x0F1B20CB</albedo>
     <normal>CggLKOA_0xC5ABC8F5</normal>
     <material>ZmntaKA_0xB34408F8</material>
     <palette />
     <tint0 value="255" />
     <tint1 value="255" />
     <tint2 value="255" />
     <probability value="255" />
    </Item>
    <Item>
     <drawable>YCrOYRA_0x542C76C3</drawable>
     <albedo>nmykACA_0xF3D534E0</albedo>
     <normal>cHttHHA_0x7F0FBC8B</normal>
     <material>YXeGyEA_0x2918138C</material>
     <palette />
     <tint0 value="255" />
     <tint1 value="255" />
     <tint2 value="255" />
     <probability value="255" />
    </Item>
    <Item>
     <drawable>RMFUvJA_0x4B8F1BF6</drawable>
     <albedo>YgpkJlA_0x7480EBA5</albedo>
     <normal>egoQWKA_0xEF1656DA</normal>
     <material>vhPnvMA_0xB3581CC7</material>
     <palette />
     <tint0 value="255" />
     <tint1 value="255" />
     <tint2 value="255" />
     <probability value="255" />
    </Item>
    <Item>
     <drawable>cs_abigailroberts_fs1_veil_000</drawable>
     <albedo>hfwVOMA_0x40F19B30</albedo>
     <normal>gzxTmLA_0xE77F529D</normal>
     <material>ezmxDAA_0xF42B16E2</material>
     <palette />
     <tint0 value="255" />
     <tint1 value="255" />
     <tint2 value="255" />
     <probability value="255" />
    </Item>
   </explicitAssets>
   <expressions itemType="MetaPedExpression">
    <Item>
     <id value="16009" />
     <value value="-0.1" />
    </Item>
    <Item>
     <id value="38169" />
     <value value="-0.87" />
    </Item>
    <Item>
     <id value="9586" />
     <value value="-0.4" />
    </Item>
   </expressions>
   <subOutfits />
   <variations />
   <tags>
    <Item>DuEerZA_0x92C43393</Item>
    <Item>hTzmBfA_0x4BFA4A07</Item>
    <Item>rRHQlJA_0x2F9EEF6E</Item>
   </tags>
   <shopItems />
  </Item>
  <Item>
   <name>DfRRFRA_0xE2E8D982</name>
   <ethnicity />
   <slodDwd>ONpHuBA_0x060AE8F2</slodDwd>
   <voiceGroup />
   <damagePack />
   <goreType />
   <scale value="0" />
   <cutsceneScale value="1" />
   <scaleRandomOffset value="0" />
   <coatShine value="0" />
   <coatShineBase value="0" />
   <coatShineMin value="0" />
   <coatShineMax value="1" />
   <eyeRedness value="0" />
   <removeLimbBone>ID_INVALID</removeLimbBone>
   <fullOutfit value="False" />
   <priorityLoad value="False" />
   <preStream value="False" />
   <assets />
   <explicitAssets itemType="MetaPedDefExplicitAsset">
    <Item>
     <drawable>cs_abigailroberts_fs1_hat_002</drawable>
     <albedo>FjlHDAA_0xAA68298A</albedo>
     <normal>PxCfVMA_0xA58BFADD</normal>
     <material>jEVilDA_0xC7AA8456</material>
     <palette />
     <tint0 value="255" />
     <tint1 value="255" />
     <tint2 value="255" />
     <probability value="255" />
    </Item>
   </explicitAssets>
   <expressions />
   <subOutfits />
   <variations />
   <tags />
   <shopItems />
  </Item>
  <Item>
   <name>SbGEnCA_0x244D9D26</name>
   <ethnicity />
   <slodDwd />
   <voiceGroup />
   <damagePack />
   <goreType />
   <scale value="0" />
   <cutsceneScale value="1" />
   <scaleRandomOffset value="0" />
   <coatShine value="0" />
   <coatShineBase value="0" />
   <coatShineMin value="0" />
   <coatShineMax value="1" />
   <eyeRedness value="0" />
   <removeLimbBone>ID_INVALID</removeLimbBone>
   <fullOutfit value="False" />
   <priorityLoad value="False" />
   <preStream value="False" />
   <assets />
   <explicitAssets itemType="MetaPedDefExplicitAsset">
    <Item>
     <drawable>cs_abigailroberts_fs1_shawl_000</drawable>
     <albedo>hUnrvDA_0x357C4B14</albedo>
     <normal>RWnMnNA_0x9FED9035</normal>
     <material>KvmuBEA_0x01BE242E</material>
     <palette />
     <tint0 value="255" />
     <tint1 value="255" />
     <tint2 value="255" />
     <probability value="255" />
    </Item>
   </explicitAssets>
   <expressions />
   <subOutfits />
   <variations />
   <tags />
   <shopItems />
  </Item>
  <Item>
   <name>zLLOcJA_0xF4AE62E8</name>
   <ethnicity />
   <slodDwd />
   <voiceGroup />
   <damagePack />
   <goreType />
   <scale value="1" />
   <cutsceneScale value="0" />
   <scaleRandomOffset value="0" />
   <coatShine value="0" />
   <coatShineBase value="0" />
   <coatShineMin value="0" />
   <coatShineMax value="1" />
   <eyeRedness value="0" />
   <removeLimbBone>ID_INVALID</removeLimbBone>
   <fullOutfit value="False" />
   <priorityLoad value="False" />
   <preStream value="False" />
   <assets />
   <explicitAssets itemType="MetaPedDefExplicitAsset">
    <Item>
     <drawable>cs_abigailroberts_fs1_ring_000</drawable>
     <albedo>ThIJWAA_0xDB5A5C6A</albedo>
     <normal>HFtkkEA_0x2D0C0C74</normal>
     <material>rcYszrA_0x5BB9D003</material>
     <palette />
     <tint0 value="255" />
     <tint1 value="255" />
     <tint2 value="255" />
     <probability value="255" />
    </Item>
   </explicitAssets>
   <expressions />
   <subOutfits />
   <variations />
   <tags>
    <Item>DuEerZA_0x92C43393</Item>
    <Item>hTzmBfA_0x4BFA4A07</Item>
    <Item>rRHQlJA_0x2F9EEF6E</Item>
   </tags>
   <shopItems />
  </Item>
 </outfits>
 <voiceGroup />
 <pulverizeVfx />
 <goreType>none</goreType>
 <type>MPT_FEMALE</type>
 <version value="64" />
 <allowRandomExpressions value="False" />
</MetaPed>
