<?xml version="1.0" encoding="UTF-8"?>
<MetaPed>
 <outfits itemType="MetaPedOutfit">
  <Item>
   <name>meta_outfit_default</name>
   <ethnicity>latino</ethnicity>
   <slodDwd />
   <voiceGroup />
   <damagePack>iUdpeFA_0x98D9D1D6</damagePack>
   <goreType />
   <scale value="1" />
   <cutsceneScale value="0" />
   <scaleRandomOffset value="0" />
   <coatShine value="0" />
   <coatShineBase value="0" />
   <coatShineMin value="0" />
   <coatShineMax value="1" />
   <eyeRedness value="0" />
   <removeLimbBone>ID_INVALID</removeLimbBone>
   <fullOutfit value="True" />
   <priorityLoad value="False" />
   <preStream value="False" />
   <assets />
   <explicitAssets itemType="MetaPedDefExplicitAsset">
    <Item>
     <drawable>neckerchief_fr1_004_sbvb_center</drawable>
     <albedo>RtXxbOA_0x9DC0D2AB</albedo>
     <normal>ZpZIaaA_0xFBD18619</normal>
     <material>rEqppBA_0x8A545D59</material>
     <palette>pVOIbJA_0xF93DB0C8</palette>
     <tint0 value="76" />
     <tint1 value="76" />
     <tint2 value="73" />
     <probability value="255" />
    </Item>
    <Item>
     <drawable>ajZjbaA_0x8D5C2710</drawable>
     <albedo>IPVQADA_0x94669830</albedo>
     <normal>dqtSdGA_0x5A8B9D0D</normal>
     <material>bduzBDA_0xE054CCDA</material>
     <palette>pVOIbJA_0xF93DB0C8</palette>
     <tint0 value="53" />
     <tint1 value="49" />
     <tint2 value="21" />
     <probability value="255" />
    </Item>
    <Item>
     <drawable>pant_fr1_605_alt_cinch</drawable>
     <albedo>GIVdzCA_0xEF7B1988</albedo>
     <normal>GUdAjFB_0xAF6B0554</normal>
     <material>YmMhUGA_0x1267C9C4</material>
     <palette>OCycVJA_0xF509C745</palette>
     <tint0 value="66" />
     <tint1 value="66" />
     <tint2 value="65" />
     <probability value="255" />
    </Item>
    <Item>
     <drawable>boot_fr1_606_under</drawable>
     <albedo>boot_mr1_000_c3_999_ab</albedo>
     <normal>LVqzBWA_0x5862C3FA</normal>
     <material>XgLAuAA_0x2F4F0F19</material>
     <palette>OCycVJA_0xF509C745</palette>
     <tint0 value="9" />
     <tint1 value="9" />
     <tint2 value="9" />
     <probability value="255" />
    </Item>
    <Item>
     <drawable>hat_mr1_049_alt02</drawable>
     <albedo>roWyoLA_0x77985A05</albedo>
     <normal>RbhiAPA_0xD37112A3</normal>
     <material>OqpPqCA_0xE0BFF37F</material>
     <palette>OCycVJA_0xF509C745</palette>
     <tint0 value="3" />
     <tint1 value="43" />
     <tint2 value="3" />
     <probability value="255" />
    </Item>
    <Item>
     <drawable>hair_fr1_057</drawable>
     <albedo>hair_gen_999_c0_999_ab</albedo>
     <normal>hair_gen_999_c0_999_nm</normal>
     <material>hair_gen_999_c0_999_m</material>
     <palette>gCrTlMA_0xDFB1F64C</palette>
     <tint0 value="9" />
     <tint1 value="9" />
     <tint2 value="9" />
     <probability value="255" />
    </Item>
    <Item>
     <drawable>teeth_fr1_0000</drawable>
     <albedo>WpFeUCA_0x1F790739</albedo>
     <normal>teeth_gen_0000_c0_000_nm</normal>
     <material>teeth_gen_0000_c0_000_m</material>
     <palette />
     <tint0 value="0" />
     <tint1 value="0" />
     <tint2 value="0" />
     <probability value="255" />
    </Item>
    <Item>
     <drawable>head_fr1_2015</drawable>
     <albedo>head_fr1_sc02_rough_c0_004_ab</albedo>
     <normal>head_fr1_weathered_004_nm</normal>
     <material>head_fr1_sc08_c0_000_m</material>
     <palette>NReZaHA_0x9AC34F34</palette>
     <tint0 value="0" />
     <tint1 value="0" />
     <tint2 value="0" />
     <probability value="255" />
    </Item>
    <Item>
     <drawable>gOEaOBA_0xD576FDBE</drawable>
     <albedo>hand_fr1_000_c0_002_ab</albedo>
     <normal>hand_fr1_000_c0_000_nm</normal>
     <material>hand_fr1_000_c0_000_m</material>
     <palette>NReZaHA_0x9AC34F34</palette>
     <tint0 value="21" />
     <tint1 value="21" />
     <tint2 value="21" />
     <probability value="255" />
    </Item>
    <Item>
     <drawable>eyes_fr1_0000</drawable>
     <albedo>OkSfiGA_0xBD10D52A</albedo>
     <normal>eyes_gen_0000_c0_000_nm</normal>
     <material>eyes_gen_0000_c0_000_m</material>
     <palette>oHtroKA_0xA4CFABD0</palette>
     <tint0 value="2" />
     <tint1 value="45" />
     <tint2 value="45" />
     <probability value="255" />
    </Item>
   </explicitAssets>
   <expressions itemType="MetaPedExpression">
    <Item>
     <id value="41478" />
     <value value="0.3" />
    </Item>
    <Item>
     <id value="8420" />
     <value value="0.1" />
    </Item>
    <Item>
     <id value="16009" />
     <value value="-0.1" />
    </Item>
    <Item>
     <id value="38169" />
     <value value="-0.9" />
    </Item>
    <Item>
     <id value="9586" />
     <value value="-0.8" />
    </Item>
    <Item>
     <id value="46032" />
     <value value="0.1" />
    </Item>
    <Item>
     <id value="27779" />
     <value value="-0.3" />
    </Item>
    <Item>
     <id value="64834" />
     <value value="0.1" />
    </Item>
    <Item>
     <id value="42067" />
     <value value="0.2" />
    </Item>
    <Item>
     <id value="50039" />
     <value value="-0.4" />
    </Item>
    <Item>
     <id value="7010" />
     <value value="0.2" />
    </Item>
    <Item>
     <id value="34006" />
     <value value="-0.1" />
    </Item>
    <Item>
     <id value="41396" />
     <value value="-0.4" />
    </Item>
    <Item>
     <id value="13059" />
     <value value="-1" />
    </Item>
    <Item>
     <id value="36106" />
     <value value="-0.7" />
    </Item>
    <Item>
     <id value="60334" />
     <value value="0.3" />
    </Item>
    <Item>
     <id value="15375" />
     <value value="0.8" />
    </Item>
    <Item>
     <id value="50098" />
     <value value="-0.402" />
    </Item>
    <Item>
     <id value="58147" />
     <value value="0.4" />
    </Item>
    <Item>
     <id value="35627" />
     <value value="-1" />
    </Item>
    <Item>
     <id value="7019" />
     <value value="-0.3" />
    </Item>
    <Item>
     <id value="60996" />
     <value value="-1" />
    </Item>
    <Item>
     <id value="53862" />
     <value value="0.4" />
    </Item>
    <Item>
     <id value="56827" />
     <value value="0.1" />
    </Item>
    <Item>
     <id value="28287" />
     <value value="0.3" />
    </Item>
    <Item>
     <id value="13425" />
     <value value="0.1" />
    </Item>
    <Item>
     <id value="13489" />
     <value value="0.1" />
    </Item>
    <Item>
     <id value="22046" />
     <value value="0.7" />
    </Item>
    <Item>
     <id value="16653" />
     <value value="0.8" />
    </Item>
    <Item>
     <id value="6656" />
     <value value="-0.7" />
    </Item>
    <Item>
     <id value="47949" />
     <value value="-0.6" />
    </Item>
    <Item>
     <id value="23830" />
     <value value="0.4" />
    </Item>
    <Item>
     <id value="36277" />
     <value value="-0.1" />
    </Item>
    <Item>
     <id value="60890" />
     <value value="0.2" />
    </Item>
   </expressions>
   <subOutfits />
   <variations />
   <tags />
   <shopItems />
  </Item>
 </outfits>
 <voiceGroup />
 <pulverizeVfx />
 <goreType />
 <type>MPT_FEMALE</type>
 <version value="18" />
 <allowRandomExpressions value="False" />
</MetaPed>
