<?xml version="1.0" encoding="UTF-8"?>
<MetaPed>
 <outfits itemType="MetaPedOutfit">
  <Item>
   <name>meta_outfit_default</name>
   <ethnicity>ckjaZQA_0x2EFA64A9</ethnicity>
   <slodDwd />
   <voiceGroup />
   <damagePack />
   <goreType />
   <scale value="1" />
   <cutsceneScale value="0" />
   <scaleRandomOffset value="0" />
   <coatShine value="0" />
   <coatShineBase value="0" />
   <coatShineMin value="0" />
   <coatShineMax value="1" />
   <eyeRedness value="0.6" />
   <removeLimbBone>ID_INVALID</removeLimbBone>
   <fullOutfit value="True" />
   <priorityLoad value="False" />
   <preStream value="False" />
   <assets />
   <explicitAssets itemType="MetaPedDefExplicitAsset">
    <Item>
     <drawable>combocoat_mr1_006</drawable>
     <albedo>gakvbFA_0xED87C56D</albedo>
     <normal>kvoUHBA_0x8EED5FA5</normal>
     <material>ZoClpQA_0x9412B4A8</material>
     <palette>pVOIbJA_0xF93DB0C8</palette>
     <tint0 value="155" />
     <tint1 value="16" />
     <tint2 value="52" />
     <probability value="255" />
    </Item>
    <Item>
     <drawable>tuxlower_mr1_000_alt01</drawable>
     <albedo>CMzCzrA_0xFB88C13C</albedo>
     <normal>IZQvHdA_0xF1A658B2</normal>
     <material>XZHwgJA_0x93E0FBA7</material>
     <palette>OCycVJA_0xF509C745</palette>
     <tint0 value="188" />
     <tint1 value="0" />
     <tint2 value="22" />
     <probability value="255" />
    </Item>
    <Item>
     <drawable>hair_mr1_088</drawable>
     <albedo>uFiPbBA_0x8C2F7AAB</albedo>
     <normal>idtaCBA_0x78F19666</normal>
     <material>RNTIxSA_0x4DD00D39</material>
     <palette>gCrTlMA_0xDFB1F64C</palette>
     <tint0 value="9" />
     <tint1 value="9" />
     <tint2 value="9" />
     <probability value="255" />
    </Item>
    <Item>
     <drawable>hat_mr1_063_alt02</drawable>
     <albedo>hat_mr1_063_c3_999_ab</albedo>
     <normal>hat_mr1_063_c3_000_nm</normal>
     <material>hat_mr1_063_c3_000_m</material>
     <palette>nXfDmZA_0x3385C5DB</palette>
     <tint0 value="51" />
     <tint1 value="49" />
     <tint2 value="55" />
     <probability value="255" />
    </Item>
    <Item>
     <drawable>uppertorso_mr1_001</drawable>
     <albedo>gOCGwKA_0x14AA7AC1</albedo>
     <normal>hand_mr1_000_c0_000_nm</normal>
     <material>xEhIahA_0x6B504BEC</material>
     <palette>nYcslHA_0xAA65D8A3</palette>
     <tint0 value="0" />
     <tint1 value="0" />
     <tint2 value="0" />
     <probability value="255" />
    </Item>
    <Item>
     <drawable>teeth_mr1_0000</drawable>
     <albedo>WpFeUCA_0x1F790739</albedo>
     <normal>teeth_gen_0000_c0_000_nm</normal>
     <material>teeth_gen_0000_c0_000_m</material>
     <palette>hSqBDbA_0xD1476963</palette>
     <tint0 value="0" />
     <tint1 value="0" />
     <tint2 value="0" />
     <probability value="255" />
    </Item>
    <Item>
     <drawable>head_mr1_1027</drawable>
     <albedo>head_mr1_sc05_rough_c0_001_ab</albedo>
     <normal>head_mr1_aged_000_nm</normal>
     <material>head_mr1_sc08_c0_000_m</material>
     <palette>NReZaHA_0x9AC34F34</palette>
     <tint0 value="0" />
     <tint1 value="0" />
     <tint2 value="0" />
     <probability value="255" />
    </Item>
    <Item>
     <drawable>eyes_mr1_0000</drawable>
     <albedo>OkSfiGA_0xBD10D52A</albedo>
     <normal>eyes_gen_0000_c0_000_nm</normal>
     <material>eyes_gen_0000_c0_000_m</material>
     <palette>oHtroKA_0xA4CFABD0</palette>
     <tint0 value="2" />
     <tint1 value="45" />
     <tint2 value="45" />
     <probability value="255" />
    </Item>
   </explicitAssets>
   <expressions itemType="MetaPedExpression">
    <Item>
     <id value="52553" />
     <value value="-0.054" />
    </Item>
    <Item>
     <id value="3437" />
     <value value="-0.3" />
    </Item>
    <Item>
     <id value="16009" />
     <value value="-0.1" />
    </Item>
    <Item>
     <id value="38169" />
     <value value="-0.8" />
    </Item>
    <Item>
     <id value="9586" />
     <value value="-0.2" />
    </Item>
    <Item>
     <id value="49787" />
     <value value="-1" />
    </Item>
    <Item>
     <id value="34006" />
     <value value="-0.5" />
    </Item>
    <Item>
     <id value="41396" />
     <value value="-0.6" />
    </Item>
    <Item>
     <id value="13059" />
     <value value="-1" />
    </Item>
    <Item>
     <id value="12281" />
     <value value="0.3" />
    </Item>
    <Item>
     <id value="19153" />
     <value value="0.3" />
    </Item>
    <Item>
     <id value="27147" />
     <value value="-0.5" />
    </Item>
    <Item>
     <id value="43983" />
     <value value="-0.3" />
    </Item>
    <Item>
     <id value="50098" />
     <value value="-0.2" />
    </Item>
    <Item>
     <id value="58147" />
     <value value="-0.5" />
    </Item>
    <Item>
     <id value="60996" />
     <value value="-1" />
    </Item>
    <Item>
     <id value="53862" />
     <value value="0.2" />
    </Item>
    <Item>
     <id value="42318" />
     <value value="0.1" />
    </Item>
    <Item>
     <id value="56827" />
     <value value="-0.7" />
    </Item>
    <Item>
     <id value="13425" />
     <value value="0.6" />
    </Item>
    <Item>
     <id value="1013" />
     <value value="-0.7" />
    </Item>
    <Item>
     <id value="13489" />
     <value value="-0.2" />
    </Item>
    <Item>
     <id value="61782" />
     <value value="-0.1" />
    </Item>
    <Item>
     <id value="22046" />
     <value value="-0.1" />
    </Item>
    <Item>
     <id value="61541" />
     <value value="0.7" />
    </Item>
    <Item>
     <id value="43625" />
     <value value="0.6" />
    </Item>
    <Item>
     <id value="31427" />
     <value value="0.2" />
    </Item>
    <Item>
     <id value="16653" />
     <value value="0.4" />
    </Item>
   </expressions>
   <subOutfits />
   <variations />
   <tags>
    <Item>zDZGgYA_0xEC442508</Item>
    <Item>GdjvpiA_0x54E4A994</Item>
    <Item>dYNtiRA_0x80DF2E2E</Item>
   </tags>
   <shopItems />
  </Item>
 </outfits>
 <voiceGroup />
 <pulverizeVfx />
 <goreType />
 <type>MPT_MALE</type>
 <version value="19" />
 <allowRandomExpressions value="False" />
</MetaPed>
